README.rst
setup.cfg
setup.py
src/extmods/fastint.c
src/extmods/faststructure.c
src/extmods/utils.c
src/plum_boost/__init__.py
src/plum_boost.egg-info/PKG-INFO
src/plum_boost.egg-info/SOURCES.txt
src/plum_boost.egg-info/dependency_links.txt
src/plum_boost.egg-info/requires.txt
src/plum_boost.egg-info/top_level.txt
src/plum_boost.egg-info/zip-safe